{
  "version": 1,
  "updatedAt": "2026-06-02T02:13:59.314Z",
  "items": [
    {
      "id": "AXTI-2025-05-14-validation",
      "ticker": "AXTI",
      "name": "AXT Inc.",
      "date": "2025-05-14",
      "eventType": "validation",
      "source": "yahoo_finance",
      "sourceUrl": "https://finance.yahoo.com/quote/AXTI/history/",
      "observedAt": "2025-05-14",
      "priceAtEvent": 1.44,
      "summary": "InP backlog 与 InP revenue 同时进入可追踪状态",
      "confidence": "high",
      "status": "verified"
    },
    {
      "id": "SIVE-2024-11-12-validation",
      "ticker": "SIVE",
      "name": "Sivers Semiconductors",
      "date": "2024-11-12",
      "eventType": "validation",
      "source": "manual_estimate",
      "sourceUrl": "https://stockanalysis.com/quote/sto/SIVE/history/",
      "observedAt": "2024-11-12",
      "priceAtEvent": 4.78,
      "summary": "CPO/ELS pipeline 变成资本可追踪的商业机会池",
      "confidence": "medium",
      "status": "estimate"
    },
    {
      "id": "POET-2025-10-21-validation",
      "ticker": "POET",
      "name": "POET Technologies",
      "date": "2025-10-21",
      "eventType": "validation",
      "source": "eodhd",
      "sourceUrl": "",
      "observedAt": "2025-10-21",
      "priceAtEvent": 7.45,
      "summary": "Lumilens PO 让平台路线从故事进入订单线索",
      "confidence": "high",
      "status": "verified"
    },
    {
      "id": "VECO-2026-04-24-validation",
      "ticker": "VECO",
      "name": "Veeco Instruments",
      "date": "2026-04-24",
      "eventType": "validation",
      "source": "eodhd",
      "sourceUrl": "",
      "observedAt": "2026-04-24",
      "priceAtEvent": 51.73,
      "summary": "InP laser equipment 大订单确认上游设备瓶颈",
      "confidence": "high",
      "status": "verified"
    },
    {
      "id": "AAOI-2025-06-17-validation",
      "ticker": "AAOI",
      "name": "Applied Optoelectronics",
      "date": "2025-06-17",
      "eventType": "validation",
      "source": "eodhd",
      "sourceUrl": "",
      "observedAt": "2025-06-17",
      "priceAtEvent": 16.78,
      "summary": "AI optical revenue 与客户供货线索进入财报验证",
      "confidence": "high",
      "status": "verified"
    },
    {
      "id": "MU-2024-06-26-validation",
      "ticker": "MU",
      "name": "Micron Technology",
      "date": "2024-06-26",
      "eventType": "validation",
      "source": "businessquant_fintel",
      "sourceUrl": "https://businessquant.com/metrics/mu/price",
      "observedAt": "2024-06-26",
      "priceAtEvent": 142.36,
      "summary": "HBM sold-out、毛利与指引上修形成财报验证",
      "confidence": "medium",
      "status": "estimate"
    },
    {
      "id": "XFAB-2026-04-30-validation",
      "ticker": "XFAB",
      "name": "X-FAB",
      "date": "2026-04-30",
      "eventType": "validation",
      "source": "eodhd",
      "sourceUrl": "",
      "observedAt": "2026-04-30",
      "priceAtEvent": 6.29,
      "summary": "WBG 与 photonics 增速开始抵消传统业务拖累",
      "confidence": "high",
      "status": "verified"
    },
    {
      "id": "CAMT-2025-12-10-validation",
      "ticker": "CAMT",
      "name": "Camtek",
      "date": "2025-12-10",
      "eventType": "validation",
      "source": "eodhd",
      "sourceUrl": "",
      "observedAt": "2025-12-10",
      "priceAtEvent": 121.12,
      "summary": "HBM/advanced packaging 检测订单提供需求验证",
      "confidence": "high",
      "status": "verified"
    },
    {
      "id": "BESI.AS-2026-04-18-validation",
      "ticker": "BESI.AS",
      "name": "BE Semiconductor Industries",
      "date": "2026-04-18",
      "eventType": "validation",
      "source": "manual_seed",
      "sourceUrl": "",
      "observedAt": "2026-04-18",
      "priceAtEvent": 95,
      "summary": "hybrid bonding 订单线索进入财报和客户验证口径",
      "confidence": "medium",
      "status": "needs_source"
    },
    {
      "id": "COHR.US-2026-03-12-validation",
      "ticker": "COHR.US",
      "name": "Coherent",
      "date": "2026-03-12",
      "eventType": "validation",
      "source": "manual_seed",
      "sourceUrl": "",
      "observedAt": "2026-03-12",
      "priceAtEvent": 49.5,
      "summary": "AI datacom 需求进入收入和订单讨论",
      "confidence": "medium",
      "status": "needs_source"
    },
    {
      "id": "PRY.MI-2026-03-28-validation",
      "ticker": "PRY.MI",
      "name": "Prysmian",
      "date": "2026-03-28",
      "eventType": "validation",
      "source": "manual_seed",
      "sourceUrl": "",
      "observedAt": "2026-03-28",
      "priceAtEvent": 40,
      "summary": "电网和高压电缆 backlog 上修进入可追踪状态",
      "confidence": "medium",
      "status": "needs_source"
    }
  ]
}
